[
  {
    "Author": "OOFGames",
    "Name": "Chocobo Racing Gamba",
    "InternalName": "ChocoboRacingGamba",
    "AssemblyVersion": "0.1.5.1",
    "Description": "Players pick a chocobo(s) to bet on, the host rolls /random to advance chocobos, and the first to reach the finish line wins. Type /crg or /Chocoboracinggamba to open the main window.",
    "ApplicableVersion": "any",
    "RepoUrl": "https://github.com/OOFGamesss/OOFGamesPlugins",
    "Tags": [
      "chocobo",
      "racing",
      "minigame",
      "chat",
      "party",
      "alliance",
      "gamba"
    ],
    "DalamudApiLevel": 15,
    "LoadRequiredState": 0,
    "LoadSync": false,
    "CanUnloadAsync": false,
    "LoadPriority": 0,
    "IconUrl": "https://raw.githubusercontent.com/OOFGamesss/OOFGamesPlugins/main/images/chocoboracinggamba.png",
    "Punchline": "Host Chocobo Racing Gamba with your friends in Eorzea!",
    "Changelog": "Bug:\n- Fixed issue where if bet was equal to max bet then it would treat it as over max bet.",
    "AcceptsFeedback": true,
    "DownloadLinkInstall": "https://raw.githubusercontent.com/OOFGamesss/OOFGamesPlugins/main/ChocoboRacingGamba/latest.zip",
    "DownloadLinkUpdate": "https://raw.githubusercontent.com/OOFGamesss/OOFGamesPlugins/main/ChocoboRacingGamba/latest.zip",
    "DownloadLinkTesting": "https://raw.githubusercontent.com/OOFGamesss/OOFGamesPlugins/main/ChocoboRacingGamba/latest.zip"
  },
  {
    "Author": "OOFGames",
    "Name": "Gamba Where",
    "InternalName": "GambaWhere",
    "AssemblyVersion": "0.0.18.0",
    "Description": "Browse active gambling events across Eorzea or host your own session. Use /gambawhere to open the interface.",
    "ApplicableVersion": "any",
    "Tags": [
      "gambling",
      "events",
      "gamba",
      "hosting"
    ],
    "DalamudApiLevel": 15,
    "LoadRequiredState": 0,
    "LoadSync": false,
    "CanUnloadAsync": false,
    "LoadPriority": 0,
    "IconUrl": "https://raw.githubusercontent.com/OOFGamesss/OOFGamesPlugins/main/images/gambawhere.png",
    "Punchline": "Find and host FFXIV gambling events near you.",
    "Changelog": "- Added new button designs to the plugin.",
    "AcceptsFeedback": true,
    "DownloadLinkInstall": "https://github.com/OOFGamesss/GambaWhere/releases/latest/download/latest.zip",
    "DownloadLinkUpdate": "https://github.com/OOFGamesss/GambaWhere/releases/latest/download/latest.zip",
    "DownloadLinkTesting": "https://github.com/OOFGamesss/GambaWhere/releases/latest/download/latest.zip"
  },
  {
    "Author": "OOFGames",
    "Name": "Mini Games Emporium",
    "InternalName": "MiniGamesEmporium",
    "AssemblyVersion": "0.0.3.1",
    "Description": "A plugin to manage mini game sessions, player queues, and Gil transactions. Use /minigames to open the main window.",
    "ApplicableVersion": "any",
    "RepoUrl": "https://github.com/OOFGamesss/MiniGamesEmporium",
    "Tags": [
      "minigames",
      "bar777",
      "queue",
      "gil",
      "gamba",
      "chat"
    ],
    "DalamudApiLevel": 15,
    "LoadRequiredState": 0,
    "LoadSync": false,
    "CanUnloadAsync": false,
    "LoadPriority": 0,
    "IconUrl": "https://raw.githubusercontent.com/OOFGamesss/OOFGamesPlugins/main/images/minigamesemporium.png",
    "Punchline": "Host BAR 777 and other mini games with automated queue management.",
    "Changelog": "- Updated button colour methed to ImRaii.",
    "AcceptsFeedback": true,
    "DownloadLinkInstall": "https://github.com/OOFGamesss/MiniGamesEmporium/releases/latest/download/latest.zip",
    "DownloadLinkUpdate": "https://github.com/OOFGamesss/MiniGamesEmporium/releases/latest/download/latest.zip",
    "DownloadLinkTesting": "https://github.com/OOFGamesss/MiniGamesEmporium/releases/latest/download/latest.zip"
  }
]
